init_proj/__init__.py
init_proj/__main__.py
init_proj/_progs.py
init_proj/drafts/gitignore.txt
init_proj/drafts/init.txt
init_proj/drafts/license.txt
init_proj/drafts/main.txt
init_proj-1.4.1.dist-info/LICENSE.txt
init_proj-1.4.1.dist-info/METADATA
init_proj-1.4.1.dist-info/WHEEL
init_proj-1.4.1.dist-info/top_level.txt
init_proj-1.4.1.dist-info/RECORD
