Metadata-Version: 2.1
Name: init_proj
Version: 1.4.1
Summary: Create a minimal python package.
Author-email: Johannes Programming <johannes-programming@posteo.org>
License: The MIT License (MIT)
Project-URL: Download, https://pypi.org/project/init-proj/#files
Project-URL: Source, https://github.com/johannes-programming/init_proj
Classifier: License :: OSI Approved :: MIT License
Classifier: Programming Language :: Python
Classifier: Programming Language :: Python :: 3
Requires-Python: >=3.11
License-File: LICENSE.txt
Requires-Dist: fileunity >=1.1
